{"v":1,"groups":{"A":{"Mexique_Corée du Sud":{"h":0,"a":1},"Mexique_Afrique du Sud":{"h":1,"a":0},"Mexique_Tchéquie":{"h":1,"a":1},"Corée du Sud_Afrique du Sud":{"h":1,"a":0},"Corée du Sud_Tchéquie":{"h":1,"a":0},"Afrique du Sud_Tchéquie":{"h":0,"a":1}},"B":{"Canada_Suisse":{"h":1,"a":0},"Canada_Qatar":{"h":1,"a":0},"Canada_Bosnie-Herzégovine":{"h":0,"a":1},"Suisse_Qatar":{"h":1,"a":0},"Suisse_Bosnie-Herzégovine":{"h":0,"a":1},"Qatar_Bosnie-Herzégovine":{"h":0,"a":1}},"C":{"Brésil_Maroc":{"h":0,"a":1},"Brésil_Écosse":{"h":1,"a":0},"Brésil_Haïti":{"h":1,"a":0},"Maroc_Écosse":{"h":1,"a":1},"Maroc_Haïti":{"h":1,"a":0}},"D":{"États-Unis_Paraguay":{"h":1,"a":0},"États-Unis_Turquie":{"h":1,"a":0},"États-Unis_Australie":{"h":1,"a":1},"Paraguay_Australie":{"h":0,"a":1},"Paraguay_Turquie":{"h":0,"a":1},"Australie_Turquie":{"h":1,"a":0}},"E":{"Allemagne_Côte d'Ivoire":{"h":1,"a":0},"Allemagne_Curaçao":{"h":1,"a":0},"Équateur_Côte d'Ivoire":{"h":0,"a":1},"Équateur_Curaçao":{"h":1,"a":0},"Côte d'Ivoire_Curaçao":{"h":1,"a":0}},"F":{"Pays-Bas_Japon":{"h":1,"a":0},"Pays-Bas_Tunisie":{"h":1,"a":0},"Pays-Bas_Suède":{"h":1,"a":0},"Japon_Tunisie":{"h":1,"a":0},"Japon_Suède":{"h":1,"a":1},"Tunisie_Suède":{"h":1,"a":1}},"G":{"Belgique_Iran":{"h":1,"a":1},"Belgique_Égypte":{"h":1,"a":0},"Belgique_Nouvelle-Zélande":{"h":1,"a":0},"Iran_Égypte":{"h":1,"a":1},"Iran_Nouvelle-Zélande":{"h":1,"a":1},"Égypte_Nouvelle-Zélande":{"h":1,"a":0}},"H":{"Espagne_Uruguay":{"h":1,"a":1},"Espagne_Cap-Vert":{"h":1,"a":0},"Espagne_Arabie saoudite":{"h":1,"a":0},"Uruguay_Cap-Vert":{"h":1,"a":0},"Uruguay_Arabie saoudite":{"h":1,"a":0},"Cap-Vert_Arabie saoudite":{"h":0,"a":1}},"I":{"France_Sénégal":{"h":1,"a":1},"France_Irak":{"h":1,"a":0},"France_Norvège":{"h":1,"a":1},"Sénégal_Norvège":{"h":1,"a":1},"Sénégal_Irak":{"h":1,"a":0},"Norvège_Irak":{"h":1,"a":0}},"J":{"Argentine_Algérie":{"h":1,"a":0},"Argentine_Autriche":{"h":1,"a":0},"Argentine_Jordanie":{"h":1,"a":0},"Algérie_Autriche":{"h":1,"a":0},"Algérie_Jordanie":{"h":1,"a":0},"Autriche_Jordanie":{"h":1,"a":1}},"L":{"Angleterre_Croatie":{"h":0,"a":1},"Angleterre_Ghana":{"h":1,"a":1},"Angleterre_Panama":{"h":1,"a":0},"Croatie_Ghana":{"h":1,"a":0},"Croatie_Panama":{"h":1,"a":0},"Ghana_Panama":{"h":1,"a":0}}},"ko":{},"nom":"jp","date":"10/06/2026"}